ckanext_boe-0.0.2-py3.10-nspkg.pth
ckanext/boe/__init__.py
ckanext/boe/cli.py
ckanext/boe/helpers.py
ckanext/boe/plugin.py
ckanext/boe/views.py
ckanext/boe/assets/script.js
ckanext/boe/assets/style.css
ckanext/boe/assets/webassets.yml
ckanext/boe/tests/__init__.py
ckanext/boe/tests/test_helpers.py
ckanext/boe/tests/test_plugin.py
ckanext/boe/tests/test_views.py
ckanext/boe/utils/__init__.py
ckanext/boe/utils/db.py
ckanext/boe/utils/scrap.py
ckanext_boe-0.0.2.dist-info/LICENSE
ckanext_boe-0.0.2.dist-info/METADATA
ckanext_boe-0.0.2.dist-info/WHEEL
ckanext_boe-0.0.2.dist-info/entry_points.txt
ckanext_boe-0.0.2.dist-info/namespace_packages.txt
ckanext_boe-0.0.2.dist-info/top_level.txt
ckanext_boe-0.0.2.dist-info/RECORD
