Metadata-Version: 2.1
Name: ckanext-boe
Version: 0.0.2
Summary: UNKNOWN
Author: Sergey Motornyuk
Author-email: sergey.motornyuk@linkdigital.com.au
License: AGPL
Keywords: CKAN
Platform: UNKNOWN
Classifier: Development Status :: 4 - Beta
Classifier: License :: OSI Approved :: GNU Affero General Public License v3 or later (AGPLv3+)
Classifier: Programming Language :: Python :: 3.7
Classifier: Programming Language :: Python :: 3.8
Classifier: Programming Language :: Python :: 3.9
Classifier: Programming Language :: Python :: 3.10
License-File: LICENSE
Requires-Dist: beautifulsoup4
Requires-Dist: soupsieve
Requires-Dist: typing-extensions
Requires-Dist: ckanext-toolbelt
